{
  "recentFiles": [
    {
      "basename": "Thalassemia",
      "path": "USMLE/Blood/Thalassemia.md"
    },
    {
      "basename": "Cushing syndrome",
      "path": "USMLE/Endocrine/Cushing syndrome.md"
    },
    {
      "basename": "Adrenal insufficiency",
      "path": "USMLE/Endocrine/Adrenal insufficiency.md"
    },
    {
      "basename": "Lab Values",
      "path": "USMLE/Lab Values.md"
    },
    {
      "basename": "Lactose intolerance",
      "path": "USMLE/GI/Lactose intolerance.md"
    },
    {
      "basename": "Stool osmotic gap",
      "path": "USMLE/GI/Stool osmotic gap.md"
    },
    {
      "basename": "Hyperparathyroidism",
      "path": "USMLE/Endocrine/Hyperparathyroidism.md"
    },
    {
      "basename": "Hypercalcemia",
      "path": "USMLE/Cardiology/Hypercalcemia.md"
    },
    {
      "basename": "Polycystic ovary syndrome",
      "path": "USMLE/Reproductive/Polycystic ovary syndrome.md"
    },
    {
      "basename": "Anorexia nervosa",
      "path": "USMLE/Psychiatry/Anorexia nervosa.md"
    },
    {
      "basename": "Euthyroid sick syndrome",
      "path": "USMLE/Endocrine/Euthyroid sick syndrome.md"
    },
    {
      "basename": "Alpha-1 antitrypsin deficiency",
      "path": "USMLE/Respiratory/Alpha-1 antitrypsin deficiency.md"
    },
    {
      "basename": "Syndrome of inappropriate antidiuretic hormone secretion",
      "path": "USMLE/Neurology/Syndrome of inappropriate antidiuretic hormone secretion.md"
    },
    {
      "basename": "Renal physiology",
      "path": "USMLE/Renal/Renal physiology.md"
    },
    {
      "basename": "Diabetes insipidus",
      "path": "USMLE/Renal/Diabetes insipidus.md"
    },
    {
      "basename": "Urine specific gravity",
      "path": "USMLE/Renal/Urine specific gravity.md"
    },
    {
      "basename": "Urine osmolality",
      "path": "USMLE/Renal/Urine osmolality.md"
    },
    {
      "basename": "Alopecia",
      "path": "USMLE/MSK/Alopecia.md"
    },
    {
      "basename": "Acanthosis nigricans",
      "path": "USMLE/MSK/Acanthosis nigricans.md"
    },
    {
      "basename": "Vitamin B12",
      "path": "USMLE/Biochemistry/Vitamin B12.md"
    },
    {
      "basename": "Maple syrup urine disease",
      "path": "USMLE/Biochemistry/Maple syrup urine disease.md"
    },
    {
      "basename": "Pasted image 20231117163430",
      "path": "appendix/Pasted image 20231117163430.png"
    },
    {
      "basename": "Urea cycle",
      "path": "USMLE/Biochemistry/Urea cycle.md"
    },
    {
      "basename": "Pasted image 20231108214012",
      "path": "appendix/Pasted image 20231108214012.png"
    },
    {
      "basename": "HMP shunt",
      "path": "USMLE/Biochemistry/HMP shunt.md"
    },
    {
      "basename": "Pasted image 20231113170927",
      "path": "appendix/Pasted image 20231113170927.png"
    },
    {
      "basename": "De Novo Purine Synthesis - OG copy",
      "path": "appendix/De Novo Purine Synthesis - OG copy.png"
    },
    {
      "basename": "Homocystinuria",
      "path": "USMLE/Biochemistry/Homocystinuria.md"
    },
    {
      "basename": "Pasted image 20231111104739",
      "path": "appendix/Pasted image 20231111104739.png"
    },
    {
      "basename": "Vitamin B7",
      "path": "USMLE/Biochemistry/Vitamin B7.md"
    },
    {
      "basename": "Pasted image 20231107160524",
      "path": "appendix/Pasted image 20231107160524.png"
    },
    {
      "basename": "Acute appendicitis",
      "path": "USMLE/GI/Acute appendicitis.md"
    },
    {
      "basename": "Stomach histology",
      "path": "USMLE/GI/Stomach histology.md"
    },
    {
      "basename": "Meniere disease",
      "path": "USMLE/Neurology/Meniere disease.md"
    },
    {
      "basename": "Li-Fraumeni syndrome",
      "path": "USMLE/Pathology/Li-Fraumeni syndrome.md"
    },
    {
      "basename": "Oral white lesions",
      "path": "USMLE/MSK/Oral white lesions.md"
    },
    {
      "basename": "Ulcerative colitis",
      "path": "USMLE/GI/Ulcerative colitis.md"
    },
    {
      "basename": "Peptic ulcer disease",
      "path": "USMLE/GI/Peptic ulcer disease.md"
    },
    {
      "basename": "Liver zones",
      "path": "USMLE/GI/Liver zones.md"
    },
    {
      "basename": "Halothane hepatitis",
      "path": "USMLE/GI/Halothane hepatitis.md"
    },
    {
      "basename": "Nonalcoholic fatty liver disease",
      "path": "USMLE/GI/Nonalcoholic fatty liver disease.md"
    },
    {
      "basename": "Alcoholic hepatitis",
      "path": "USMLE/GI/Alcoholic hepatitis.md"
    },
    {
      "basename": "Alkaline phosphatase",
      "path": "USMLE/Blood/Alkaline phosphatase.md"
    },
    {
      "basename": "Diabetic neuropathy",
      "path": "USMLE/Endocrine/Diabetic neuropathy.md"
    },
    {
      "basename": "Diabetes mellitus",
      "path": "USMLE/Endocrine/Diabetes mellitus.md"
    },
    {
      "basename": "Diabetic gastroparesis",
      "path": "USMLE/Endocrine/Diabetic gastroparesis.md"
    },
    {
      "basename": "Lysosomal Storage Diseases",
      "path": "USMLE/Biochemistry/Lysosomal Storage Diseases.md"
    },
    {
      "basename": "Fatty acid oxidation",
      "path": "USMLE/Biochemistry/Fatty acid oxidation.md"
    },
    {
      "basename": "Pasted image 20230722174657",
      "path": "appendix/Pasted image 20230722174657.png"
    },
    {
      "basename": "Galactose metabolism",
      "path": "USMLE/Biochemistry/Galactose metabolism.md"
    }
  ],
  "omittedPaths": [],
  "maxLength": null,
  "openType": "tab"
}